pytest_board/__init__.py
pytest_board/__main__.py
pytest_board/command.py
pytest_board/plugin.py
pytest_board/server.py
pytest_board/testrunner.py
pytest_board/util.py
pytest_board/utils.py
pytest_board/watcher.py
pytest_board/client/composer.html
pytest_board/client/favicon.ico
pytest_board/client/index.html
pytest_board/client/resources/css/common.css
pytest_board/client/resources/css/composer.css
pytest_board/client/resources/css/tipsy.css
pytest_board/client/resources/css/themes/dark-bigtext.css
pytest_board/client/resources/css/themes/dark.css
pytest_board/client/resources/css/themes/light.css
pytest_board/client/resources/fonts/FontAwesome/README.md
pytest_board/client/resources/fonts/FontAwesome/css/font-awesome.css
pytest_board/client/resources/fonts/FontAwesome/fonts/FontAwesome.otf
pytest_board/client/resources/fonts/FontAwesome/fonts/fontawesome-webfont.eot
pytest_board/client/resources/fonts/FontAwesome/fonts/fontawesome-webfont.svg
pytest_board/client/resources/fonts/FontAwesome/fonts/fontawesome-webfont.ttf
pytest_board/client/resources/fonts/FontAwesome/fonts/fontawesome-webfont.woff
pytest_board/client/resources/fonts/FontAwesome/fonts/fontawesome-webfont.woff2
pytest_board/client/resources/fonts/Open_Sans/LICENSE.txt
pytest_board/client/resources/fonts/Open_Sans/OpenSans-Bold.ttf
pytest_board/client/resources/fonts/Open_Sans/OpenSans-Italic.ttf
pytest_board/client/resources/fonts/Open_Sans/OpenSans-Light.ttf
pytest_board/client/resources/fonts/Open_Sans/OpenSans-LightItalic.ttf
pytest_board/client/resources/fonts/Open_Sans/OpenSans-Regular.ttf
pytest_board/client/resources/fonts/Orbitron/OFL.txt
pytest_board/client/resources/fonts/Orbitron/Orbitron-Regular.ttf
pytest_board/client/resources/fonts/Oswald/OFL.txt
pytest_board/client/resources/fonts/Oswald/Oswald-Regular.ttf
pytest_board/client/resources/ico/goconvey-buildfail.ico
pytest_board/client/resources/ico/goconvey-fail.ico
pytest_board/client/resources/ico/goconvey-ok.ico
pytest_board-0.1.0.dist-info/LICENSE.md
pytest_board-0.1.0.dist-info/METADATA
pytest_board-0.1.0.dist-info/WHEEL
pytest_board-0.1.0.dist-info/entry_points.txt
pytest_board-0.1.0.dist-info/top_level.txt
pytest_board-0.1.0.dist-info/RECORD
