Metadata-Version: 2.1
Name: pytest-board
Version: 0.1.0
Summary: Local continuous test runner with pytest and watchdog.
Home-page: http://github.com/kuss/pytest-board
Author: Jaeman An
Author-email: ajmbell@gmail.com
License: MIT
Platform: any
Requires-Dist: pytest-watch (==4.2.0)
